jelka_validator/__init__.py
jelka_validator/datareader.py
jelka_validator/datawriter.py
jelka_validator/utils.py
jelka_validator-1.0.2.dist-info/METADATA
jelka_validator-1.0.2.dist-info/WHEEL
jelka_validator-1.0.2.dist-info/licenses/LICENSE
jelka_validator-1.0.2.dist-info/RECORD
